fault_dft-0.9.4.dist-info/top_level.txt
fault_dft-0.9.4.dist-info/RECORD
fault_dft-0.9.4.dist-info/METADATA
fault_dft-0.9.4.dist-info/entry_points.txt
fault_dft-0.9.4.dist-info/WHEEL
fault/__main__.py
fault/fault.exe
