Metadata-Version: 2.1
Name: fault-dft
Version: 0.9.4
Summary: Open source DFT toolchain
Classifier: License :: OSI Approved :: MIT License
Classifier: Programming Language :: Python :: 3
Classifier: Intended Audience :: Developers
Classifier: Operating System :: POSIX :: Linux
Classifier: Operating System :: MacOS :: MacOS X
Requires-Python: >=3.8
Requires-Dist: wheel
Requires-Dist: setuptools
Requires-Dist: pyverilog
Requires-Dist: nl2bench>=0.9.2
Requires-Dist: find-libpython
Requires-Dist: yowasp-yosys
